Workbook

Sheet Executive Summary
A1: RESELLER HOSTING COMPETITOR PRICING REPORT — KENYA MARKET
A2: Detailed Competitive Analysis | Data as of September 2026 | Exchange Rate Assumption: 1 USD = 129.50 KES
A4: REPORT PURPOSE
A5: This spreadsheet consolidates reseller hosting pricing from major providers active in the Kenyan market (Hostnali, Truehost, Htech-solutions, Gigacore, SiteGround). Prices are normalized to both KES and USD for easy comparison. Value metrics (KES per GB and KES per cPanel account) help identify the most cost-efficient plans. Local Kenyan providers are highlighted for relevance to East African buyers.
A8: KEY FINDINGS
A9: 1. Lowest entry price: Truehost Bronze at KSh 1,500/mo (20 accounts, 30 GB) — strongest for new Kenyan resellers.
A10: 2. Hostnali offers the best local feature set at mid-tier (Free WHMCS + M-Pesa module) starting KSh 2,500.
A11: 3. International providers (SiteGround, Gigacore, Htech) appear cheaper on promo but renew at significantly higher rates and lack local payment/support advantages.
A12: 4. Best value by storage: Hostnali Budget (~KSh 50/GB); best value by accounts: Truehost Bronze (~KSh 75/account).
A13: 5. Platinum tiers diverge widely: Truehost Platinum KSh 15,000 vs Hostnali KSh 10,000 for similar account counts.
A14: 6. Critical: Always verify renewal rates, WHMCS licensing costs, and whether bandwidth is truly unmetered.
A16: SHEETS IN THIS WORKBOOK
A17: Price Comparison | B17: Master table of all plans with KES + USD pricing, disk, accounts, and key features
A18: Value Metrics | B18: Calculated cost efficiency: KES per GB and KES per cPanel account (Excel formulas)
A19: Feature Matrix | B19: Side-by-side feature checklist (WHMCS, M-Pesa, private NS, white-label, etc.)
A20: Billing Notes | B20: Important caveats on promo vs renewal pricing, hidden costs, billing cycles
A21: Competitive Insights | B21: Strategic observations for pricing your own reseller or wholesale offering
A23: DATA SOURCES & ASSUMPTIONS
A24: • Hostnali: hostnali.co.ke (confirmed KSh pricing). • Truehost: truehost.co.ke (current KSh list). • Htech-solutions, Gigacore, SiteGround: user-supplied / public USD list (converted). • Exchange rate fixed at 129.50 KES/USD for consistency (CBK mid-market ~129.4–129.5 as of Sep 2026). • All monthly prices shown; annual/triennial discounts may apply. Verify live before quoting.

Sheet Price Comparison
A1: RESELLER HOSTING PRICE COMPARISON — KENYA & INTERNATIONAL PROVIDERS
D2: FX Rate (KES/USD): | E2: 129.5 | F2: ← Edit this cell to update all USD↔KES conversions
A3: Provider | B3: Origin | C3: Plan Name | D3: Price (KSh/mo) | E3: Price (USD/mo) | F3: Disk Space (GB) | G3: cPanel Accounts | H3: KES / GB | I3: KES / Account | J3: Key Features | K3: Billing Notes | L3: Source
A4: Hostnali | B4: Kenya | C4: Budget Reseller | D4: 2500 | E4: =D4/$E$2 -> 19.305019 | F4: 50 | G4: 40 | H4: =IF(OR(F4="",F4=0),"",D4/F4) -> 50 | I4: =IF(OR(G4="",G4=0),"",D4/G4) -> 62.5 | J4: Free WHMCS, M-Pesa Module, Private NS, Unlimited BW | K4: Monthly; check annual discount | L4: hostnali.co.ke
A5: Hostnali | B5: Kenya | C5: Standard Reseller | D5: 5500 | E5: =D5/$E$2 -> 42.471042 | F5: 100 | G5: 80 | H5: =IF(OR(F5="",F5=0),"",D5/F5) -> 55 | I5: =IF(OR(G5="",G5=0),"",D5/G5) -> 68.75 | J5: Popular for new businesses; Private NS, WHMCS options | K5: Monthly | L5: hostnali.co.ke
A6: Hostnali | B6: Kenya | C6: Executive Reseller | D6: 7400 | E6: =D6/$E$2 -> 57.142857 | F6: 150 | G6: 120 | H6: =IF(OR(F6="",F6=0),"",D6/F6) -> 49.333333 | I6: =IF(OR(G6="",G6=0),"",D6/G6) -> 61.666667 | J6: Advanced; Free WHMCS, M-Pesa, Domain Reseller | K6: Monthly | L6: hostnali.co.ke
A7: Hostnali | B7: Kenya | C7: Platinum Reseller | D7: 10000 | E7: =D7/$E$2 -> 77.220077 | F7: 200 | G7: 160 | H7: =IF(OR(F7="",F7=0),"",D7/F7) -> 50 | I7: =IF(OR(G7="",G7=0),"",D7/G7) -> 62.5 | J7: Professional package; full white-label features | K7: Monthly | L7: hostnali.co.ke
A8: Truehost | B8: Kenya | C8: Bronze Reseller | D8: 1500 | E8: =D8/$E$2 -> 11.583012 | F8: 30 | G8: 20 | H8: =IF(OR(F8="",F8=0),"",D8/F8) -> 50 | I8: =IF(OR(G8="",G8=0),"",D8/G8) -> 75 | J8: Private NS, Softaculous, Unlimited BW, Instant setup | K8: Lowest entry; local support | L8: truehost.co.ke
A9: Truehost | B9: Kenya | C9: Silver Reseller | D9: 3750 | E9: =D9/$E$2 -> 28.957529 | F9: 50 | G9: 50 | H9: =IF(OR(F9="",F9=0),"",D9/F9) -> 75 | I9: =IF(OR(G9="",G9=0),"",D9/G9) -> 75 | J9: Free Domain Reseller Automation, Private NS | K9: Good mid-entry | L9: truehost.co.ke
A10: Truehost | B10: Kenya | C10: Gold Reseller | D10: 5250 | E10: =D10/$E$2 -> 40.540541 | F10: 100 | G10: 75 | H10: =IF(OR(F10="",F10=0),"",D10/F10) -> 52.5 | I10: =IF(OR(G10="",G10=0),"",D10/G10) -> 70 | J10: Private NS, Softaculous, Unlimited BW | K10: Strong mid-tier value | L10: truehost.co.ke
A11: Truehost | B11: Kenya | C11: Platinum Reseller | D11: 15000 | E11: =D11/$E$2 -> 115.83012 | F11: 150 | G11: 200 | H11: =IF(OR(F11="",F11=0),"",D11/F11) -> 100 | I11: =IF(OR(G11="",G11=0),"",D11/G11) -> 75 | J11: Highest account count among local; Private NS | K11: Premium local tier | L11: truehost.co.ke
A12: Htech-solutions | B12: International | C12: RS-1 | D12: =E12*$E$2 -> 1936.025 | E12: 14.95 | F12: 60 | G12: 20 | H12: =IF(OR(F12="",F12=0),"",D12/F12) -> 32.267083 | I12: =IF(OR(G12="",G12=0),"",D12/G12) -> 96.80125 | J12: CloudLinux, Imunify360, Free Migrations, NVMe | K12: USD pricing; migration support | L12: User list / public
A13: Gigacore.io | B13: International | C13: Reseller Vector | D13: =E13*$E$2 -> 1941.205 | E13: 14.99 | F13: 30 | G13: 10 | H13: =IF(OR(F13="",F13=0),"",D13/F13) -> 64.706833 | I13: =IF(OR(G13="",G13=0),"",D13/G13) -> 194.1205 | J13: WHMCS available (+$15.90), LiteSpeed, SiteJet AI, NVMe | K13: WHMCS extra cost | L13: gigacore.io
A14: SiteGround | B14: International | C14: GrowBig (Promo) | D14: =E14*$E$2 -> 646.205 | E14: 4.99 | F14: Unmetered* | G14: N/S | H14: N/A | I14: N/A | J14: Unmetered disk (promo), White-label capable | K14: Promo; renews ~$29.99/mo; 12-mo commit | L14: siteground.com
A15: SiteGround | B15: International | C15: GoGeek (Promo) | D15: =E15*$E$2 -> 1034.705 | E15: 7.99 | F15: Unmetered* | G15: N/S | H15: N/A | I15: N/A | J15: Unmetered disk (promo), White-label | K15: Promo; renews ~$44.99/mo; 12-mo commit | L15: siteground.com
A17: LEGEND
A18: Light blue rows = Kenyan providers (Hostnali, Truehost). Yellow cell E2 = editable FX assumption. Blue text = hardcoded inputs. Black text = Excel formulas.
A19: * SiteGround 'Unmetered' is subject to fair-use; promo prices require long-term commitment and renew at higher rates. Always verify live pricing.

Sheet Value Metrics
A1: VALUE & EFFICIENCY METRICS
A2: Lower KES/GB and KES/Account generally indicate better resource efficiency (all else equal). Values pulled via formulas from Price Comparison sheet.
A4: Ranked by approximate KES per cPanel Account (best value first among plans with defined accounts)
A5: Rank | B5: Provider | C5: Plan | D5: Price (KSh) | E5: Accounts | F5: KES / Account | G5: Disk (GB) | H5: KES / GB
A6: 1 | B6: ='Price Comparison'!A8 -> Truehost | C6: ='Price Comparison'!C8 -> Bronze Reseller | D6: ='Price Comparison'!D8 -> 1500 | E6: ='Price Comparison'!G8 -> 20 | F6: ='Price Comparison'!I8 -> 75 | G6: ='Price Comparison'!F8 -> 30 | H6: ='Price Comparison'!H8 -> 50
A7: 2 | B7: ='Price Comparison'!A4 -> Hostnali | C7: ='Price Comparison'!C4 -> Budget Reseller | D7: ='Price Comparison'!D4 -> 2500 | E7: ='Price Comparison'!G4 -> 40 | F7: ='Price Comparison'!I4 -> 62.5 | G7: ='Price Comparison'!F4 -> 50 | H7: ='Price Comparison'!H4 -> 50
A8: 3 | B8: ='Price Comparison'!A9 -> Truehost | C8: ='Price Comparison'!C9 -> Silver Reseller | D8: ='Price Comparison'!D9 -> 3750 | E8: ='Price Comparison'!G9 -> 50 | F8: ='Price Comparison'!I9 -> 75 | G8: ='Price Comparison'!F9 -> 50 | H8: ='Price Comparison'!H9 -> 75
A9: 4 | B9: ='Price Comparison'!A5 -> Hostnali | C9: ='Price Comparison'!C5 -> Standard Reseller | D9: ='Price Comparison'!D5 -> 5500 | E9: ='Price Comparison'!G5 -> 80 | F9: ='Price Comparison'!I5 -> 68.75 | G9: ='Price Comparison'!F5 -> 100 | H9: ='Price Comparison'!H5 -> 55
A10: 5 | B10: ='Price Comparison'!A10 -> Truehost | C10: ='Price Comparison'!C10 -> Gold Reseller | D10: ='Price Comparison'!D10 -> 5250 | E10: ='Price Comparison'!G10 -> 75 | F10: ='Price Comparison'!I10 -> 70 | G10: ='Price Comparison'!F10 -> 100 | H10: ='Price Comparison'!H10 -> 52.5
A11: 6 | B11: ='Price Comparison'!A6 -> Hostnali | C11: ='Price Comparison'!C6 -> Executive Reseller | D11: ='Price Comparison'!D6 -> 7400 | E11: ='Price Comparison'!G6 -> 120 | F11: ='Price Comparison'!I6 -> 61.666667 | G11: ='Price Comparison'!F6 -> 150 | H11: ='Price Comparison'!H6 -> 49.333333
A12: 7 | B12: ='Price Comparison'!A7 -> Hostnali | C12: ='Price Comparison'!C7 -> Platinum Reseller | D12: ='Price Comparison'!D7 -> 10000 | E12: ='Price Comparison'!G7 -> 160 | F12: ='Price Comparison'!I7 -> 62.5 | G12: ='Price Comparison'!F7 -> 200 | H12: ='Price Comparison'!H7 -> 50
A13: 8 | B13: ='Price Comparison'!A12 -> Htech-solutions | C13: ='Price Comparison'!C12 -> RS-1 | D13: ='Price Comparison'!D12 -> 1936.025 | E13: ='Price Comparison'!G12 -> 20 | F13: ='Price Comparison'!I12 -> 96.80125 | G13: ='Price Comparison'!F12 -> 60 | H13: ='Price Comparison'!H12 -> 32.267083
A14: 9 | B14: ='Price Comparison'!A13 -> Gigacore.io | C14: ='Price Comparison'!C13 -> Reseller Vector | D14: ='Price Comparison'!D13 -> 1941.205 | E14: ='Price Comparison'!G13 -> 10 | F14: ='Price Comparison'!I13 -> 194.1205 | G14: ='Price Comparison'!F13 -> 30 | H14: ='Price Comparison'!H13 -> 64.706833
A15: 10 | B15: ='Price Comparison'!A11 -> Truehost | C15: ='Price Comparison'!C11 -> Platinum Reseller | D15: ='Price Comparison'!D11 -> 15000 | E15: ='Price Comparison'!G11 -> 200 | F15: ='Price Comparison'!I11 -> 75 | G15: ='Price Comparison'!F11 -> 150 | H15: ='Price Comparison'!H11 -> 100
A17: INTERPRETATION
A18: • Truehost Bronze delivers the lowest cost per account — ideal for testing the reseller model with minimal capital. • Hostnali Budget offers strong storage efficiency and includes M-Pesa + WHMCS advantages valuable for Kenyan clients. • International entry plans can look cheap in USD but often lack local payment methods, Swahili support, and may have higher effective renewal costs. • Platinum tiers are about scale; compare account limits and whether overselling is permitted.

Sheet Feature Matrix
A1: FEATURE COMPARISON MATRIX
A2: ✓ = Confirmed / Included ~ = Available at extra cost or partial — = Not highlighted / Unknown
A4: Feature | B4: Hostnali | C4: Truehost | D4: Htech-solutions | E4: Gigacore.io | F4: SiteGround | G4: Notes for Kenyan Market
A5: cPanel / WHM Access | B5: ✓ | C5: ✓ | D5: ✓ | E5: ✓ | F5: ✓ (Site Tools) | G5: Standard expectation
A6: Private Nameservers | B6: ✓ | C6: ✓ | D6: ✓ | E6: ✓ | F6: ✓ | G6: Essential for white-label branding
A7: Free / Included WHMCS | B7: ✓ (higher plans) | C7: ~ / Discounted | D7: — | E7: ~ (+$15.90/mo) | F7: — | G7: Critical for automated billing in Kenya
A8: M-Pesa Payment Module | B8: ✓ | C8: ✓ (local) | D8: — | E8: — | F8: — | G8: Highly valued by Kenyan end-clients
A9: Local (Kenya) Support | B9: ✓ | C9: ✓ (24/7) | D9: — | E9: — | F9: — | G9: Major trust & conversion factor
A10: Nairobi / Regional Servers | B10: ~ | C10: ✓ (claimed) | D10: — | E10: — | F10: — | G10: Lower latency for EA users
A11: Unlimited Bandwidth | B11: ✓ | C11: ✓ | D11: ✓ | E11: ✓ | F11: Fair use | G11: Confirm fair-use policies
A12: NVMe / SSD Storage | B12: ✓ | C12: ✓ | D12: ✓ NVMe | E12: ✓ NVMe | F12: ✓ | G12: Performance differentiator
A13: Free SSL | B13: ✓ | C13: ✓ | D13: ✓ | E13: ✓ | F13: ✓ | G13: Baseline
A14: Softaculous / 1-click | B14: ✓ | C14: ✓ | D14: ✓ | E14: ✓ | F14: ✓ | G14: Ease of use for resellers
A15: White-label / Branding | B15: ✓ | C15: ✓ | D15: ✓ | E15: ✓ | F15: ✓ (higher) | G15: Core reseller need
... A20: AI / Site Builder extras | B20: ~ | C20: — | D20: — | E20: ✓ SiteJet AI | F20: ✓ | G20: Nice-to-have for non-tech clients
A23: KEY TAKEAWAY FOR LOCAL COMPETITIVENESS
A24: Hostnali and Truehost win on local relevance: M-Pesa modules, Kenyan support, and (for Truehost) claimed local infrastructure. International players compete on raw price/promo and advanced security stacks, but face higher barriers for Kenyan SMEs who prefer local payment and support. Any new entrant or pricing strategy should prioritise M-Pesa + local support + transparent KES pricing.

Sheet Billing Notes
A1: BILLING CYCLES, RENEWALS & HIDDEN COSTS
A3: Critical considerations when comparing or matching these prices
A5: Topic | B5: Detail
A6: Billing Cycle Sensitivity | B6: Many published prices (especially international) assume annual or multi-year prepay. Monthly cash-flow cost can be 20–40% higher. Always ask for pure monthly rate.
A7: Renewal Price Shock | B7: SiteGround GrowBig promo $4.99 → renews ~$29.99. GoGeek $7.99 → ~$44.99. Factor the lifetime cost, not year-1 only.
A8: WHMCS Licensing | B8: Gigacore lists WHMCS at +$15.90/mo. Hostnali includes or discounts it on higher plans. This is a major cost for serious resellers who need automated invoicing + M-Pesa.
A9: Truehost Advantage | B9: Truehost markets clear KSh monthly prices and local support — reduces surprise for local buyers.
A10: Hostnali Local Stack | B10: Free M-Pesa module + WHMCS on higher tiers is a strong differentiator vs pure international panels.
A11: Bandwidth Fair Use | B11: 'Unlimited' almost always has a fair-use clause. High-traffic client sites can trigger throttling or forced upgrades.
A12: Currency Risk | B12: USD-priced plans expose Kenyan resellers to FX volatility. KES-priced local plans provide predictability.
A13: VAT / Taxes | B13: Confirm whether displayed prices include 16% VAT. Kenyan B2B buyers often need tax-compliant invoices.
A14: Migration & Setup Fees | B14: Most list free migrations; confirm scope (number of accounts, downtime expectations).
A15: Account Limits vs Overselling | B15: Some plans allow overselling disk/accounts. This increases margin potential but also support risk if oversold aggressively.

Sheet Competitive Insights
A1: STRATEGIC COMPETITIVE INSIGHTS FOR THE KENYAN MARKET
A3: 1. Market Structure
A4: The Kenyan reseller market is price-sensitive at the entry level (KSh 1,500–3,000) and value-sensitive at mid-tier. Local providers win on payment convenience (M-Pesa), language/support, and currency stability. International players compete on promo pricing, brand recognition, and security feature depth. There is room for a well-positioned local or hybrid offering that combines transparent KES pricing, included billing automation, and reliable performance.
A7: 2. Pricing Gaps & Opportunities
A8: • Sub-KSh 2,000 entry with 30–40 accounts is currently owned by Truehost Bronze — hard to undercut profitably without scale.
A9: • Mid-tier (KSh 5,000–8,000) is crowded; differentiation must come from features (included WHMCS + M-Pesa), support quality, or uptime SLAs.
A10: • High-account Platinum (150–200 accounts) shows wide price dispersion (KSh 10k vs 15k) — opportunity to offer clearer tiered scaling.
A11: • Annual prepay discounts are expected; publishing both monthly and effective annual rates builds trust.
A13: 3. Recommended Positioning Levers
A14: • Lead with 'All prices in KSh, M-Pesa ready, no FX surprise' messaging.
A15: • Bundle a free or heavily discounted WHMCS + M-Pesa module at the Standard tier and above.
A16: • Publish clear renewal prices next to promo prices to build long-term trust.
... A21: 4. Quick Reference — Lowest Cost Plans by Metric
A22: Metric | B22: Best Plan | C22: Value
A23: Lowest absolute price | B23: Truehost Bronze | C23: KSh 1,500 / mo
A24: Best KES per Account (approx) | B24: Truehost Bronze | C24: ~KSh 75 / account
A25: Best KES per GB (approx) | B25: Hostnali Budget | C25: ~KSh 50 / GB
A26: Most accounts (local) | B26: Truehost Platinum | C26: 200 accounts
A27: Best local feature bundle | B27: Hostnali Executive+ | C27: WHMCS + M-Pesa included
A29: Disclaimer: Prices and features change frequently. This report is a point-in-time competitive snapshot for internal strategy use. Always verify live pricing and terms on provider websites before making commercial decisions or public claims.
